pyearthtools/pipeline/__init__.py
pyearthtools/pipeline/_save_pipeline.py
pyearthtools/pipeline/config.py
pyearthtools/pipeline/controller.py
pyearthtools/pipeline/decorators.py
pyearthtools/pipeline/exceptions.py
pyearthtools/pipeline/filters.py
pyearthtools/pipeline/graph.py
pyearthtools/pipeline/iterators.py
pyearthtools/pipeline/logger.py
pyearthtools/pipeline/marker.py
pyearthtools/pipeline/operation.py
pyearthtools/pipeline/parallel.py
pyearthtools/pipeline/pipeline.yaml
pyearthtools/pipeline/recording.py
pyearthtools/pipeline/samplers.py
pyearthtools/pipeline/step.py
pyearthtools/pipeline/typing.py
pyearthtools/pipeline/validation.py
pyearthtools/pipeline/warnings.py
pyearthtools/pipeline/branching/__init__.py
pyearthtools/pipeline/branching/branching.py
pyearthtools/pipeline/branching/join.py
pyearthtools/pipeline/branching/split.py
pyearthtools/pipeline/branching/stop.py
pyearthtools/pipeline/branching/unify.py
pyearthtools/pipeline/modifications/__init__.py
pyearthtools/pipeline/modifications/cache.py
pyearthtools/pipeline/modifications/idx_modification.py
pyearthtools/pipeline/operations/__init__.py
pyearthtools/pipeline/operations/transforms.py
pyearthtools/pipeline/operations/dask/__init__.py
pyearthtools/pipeline/operations/dask/augment.py
pyearthtools/pipeline/operations/dask/compute.py
pyearthtools/pipeline/operations/dask/conversion.py
pyearthtools/pipeline/operations/dask/dask.py
pyearthtools/pipeline/operations/dask/filters.py
pyearthtools/pipeline/operations/dask/join.py
pyearthtools/pipeline/operations/dask/normalisation.py
pyearthtools/pipeline/operations/dask/reshape.py
pyearthtools/pipeline/operations/dask/select.py
pyearthtools/pipeline/operations/dask/split.py
pyearthtools/pipeline/operations/dask/values.py
pyearthtools/pipeline/operations/numpy/__init__.py
pyearthtools/pipeline/operations/numpy/augment.py
pyearthtools/pipeline/operations/numpy/conversion.py
pyearthtools/pipeline/operations/numpy/filters.py
pyearthtools_pipeline-0.5.1.dist-info/METADATA
pyearthtools_pipeline-0.5.1.dist-info/WHEEL
pyearthtools_pipeline-0.5.1.dist-info/licenses/LICENSE
pyearthtools_pipeline-0.5.1.dist-info/RECORD
